<?xml version = '1.0'?>
<?xml-stylesheet type="text/xsl" href="tags.xsl"?>
<TAGLIST>
<HEADER>
<title>XYZ MakerNote Tags defined in Exiv2</title>
<text>
<p>Tags found in the MakerNote of images taken with XYZ cameras. These tags 
are defined by Exiv2 in accordance with <a href="makernote.html#RX">[X]</a>.</p>
<p>Click on a column header to sort the table.</p>
</text>
</HEADER>
<ROWSET>
   <ROW num="1">
      <tagname>ImageWidth</tagname>
      <tagdec>2</tagdec>
      <taghex>0x0002</taghex>
      <ifd>CanonPi</ifd>
      <key>Exif.CanonPi.ImageWidth</key>
      <type>Short</type>
      <tagdesc>Image width</tagdesc>
   </ROW>
   <ROW num="2">
      <tagname>ImageHeight</tagname>
      <tagdec>3</tagdec>
      <taghex>0x0003</taghex>
      <ifd>CanonPi</ifd>
      <key>Exif.CanonPi.ImageHeight</key>
      <type>Short</type>
      <tagdesc>Image height</tagdesc>
   </ROW>
   <ROW num="3">
      <tagname>ImageWidthAsShot</tagname>
      <tagdec>4</tagdec>
      <taghex>0x0004</taghex>
      <ifd>CanonPi</ifd>
      <key>Exif.CanonPi.ImageWidthAsShot</key>
      <type>Short</type>
      <tagdesc>Image width (as shot)</tagdesc>
   </ROW>
   <ROW num="4">
      <tagname>ImageHeightAsShot</tagname>
      <tagdec>5</tagdec>
      <taghex>0x0005</taghex>
      <ifd>CanonPi</ifd>
      <key>Exif.CanonPi.ImageHeightAsShot</key>
      <type>Short</type>
      <tagdesc>Image height (as shot)</tagdesc>
   </ROW>
   <ROW num="5">
      <tagname>AFPointsUsed</tagname>
      <tagdec>22</tagdec>
      <taghex>0x0016</taghex>
      <ifd>CanonPi</ifd>
      <key>Exif.CanonPi.AFPointsUsed</key>
      <type>Short</type>
      <tagdesc>AF points used</tagdesc>
   </ROW>
   <ROW num="6">
      <tagname>AFPointsUsed20D</tagname>
      <tagdec>26</tagdec>
      <taghex>0x001a</taghex>
      <ifd>CanonPi</ifd>
      <key>Exif.CanonPi.AFPointsUsed20D</key>
      <type>Short</type>
      <tagdesc>AF points used (20D)</tagdesc>
   </ROW>
</ROWSET>
</TAGLIST>
